[
  {
    "typeId": 1,
    "typeKey": "running",
    "parentTypeId": 17,
    "isHidden": false,
    "restricted": false,
    "trimmable": true
  },
  {
    "typeId": 2,
    "typeKey": "cycling",
    "parentTypeId": 17,
    "isHidden": false,
    "restricted": false,
    "trimmable": true
  },
  {
    "typeId": 3,
    "typeKey": "hiking",
    "parentTypeId": 17,
    "isHidden": false,
    "restricted": false,
    "trimmable": true
  },
  {
    "typeId": 4,
    "typeKey": "other",
    "parentTypeId": 17,
    "isHidden": false,
    "restricted": false,
    "trimmable": true
  },
  {
    "typeId": 5,
    "typeKey": "mountain_biking",
    "parentTypeId": 2,
    "isHidden": false,
    "restricted": false,
    "trimmable": true
  },
  {
    "typeId": 6,
    "typeKey": "trail_running",
    "parentTypeId": 1,
    "isHidden": false,
    "restricted": false,
    "trimmable": true
  },
  {
    "typeId": 7,
    "typeKey": "street_running",
    "parentTypeId": 1,
    "isHidden": false,
    "restricted": false,
    "trimmable": true
  },
  {
    "typeId": 8,
    "typeKey": "track_running",
    "parentTypeId": 1,
    "isHidden": false,
    "restricted": false,
    "trimmable": true
  },
  {
    "typeId": 9,
    "typeKey": "walking",
    "parentTypeId": 17,
    "isHidden": false,
    "restricted": false,
    "trimmable": true
  },
  {
    "typeId": 10,
    "typeKey": "road_biking",
    "parentTypeId": 2,
    "isHidden": false,
    "restricted": false,
    "trimmable": true
  },
  {
    "typeId": 11,
    "typeKey": "indoor_cardio",
    "parentTypeId": 29,
    "isHidden": false,
    "restricted": false,
    "trimmable": true
  },
  {
    "typeId": 13,
    "typeKey": "strength_training",
    "parentTypeId": 29,
    "isHidden": false,
    "restricted": false,
    "trimmable": false
  },
  {
    "typeId": 15,
    "typeKey": "casual_walking",
    "parentTypeId": 9,
    "isHidden": false,
    "restricted": false,
    "trimmable": true
  },
  {
    "typeId": 16,
    "typeKey": "speed_walking",
    "parentTypeId": 9,
    "isHidden": false,
    "restricted": false,
    "trimmable": true
  },
  {
    "typeId": 17,
    "typeKey": "all",
    "parentTypeId": null,
    "isHidden": false,
    "restricted": false,
    "trimmable": true
  },
  {
    "typeId": 18,
    "typeKey": "treadmill_running",
    "parentTypeId": 1,
    "isHidden": false,
    "restricted": false,
    "trimmable": true
  },
  {
    "typeId": 19,
    "typeKey": "cyclocross",
    "parentTypeId": 2,
    "isHidden": false,
    "restricted": false,
    "trimmable": true
  },
  {
    "typeId": 20,
    "typeKey": "downhill_biking",
    "parentTypeId": 2,
    "isHidden": false,
    "restricted": false,
    "trimmable": true
  },
  {
    "typeId": 21,
    "typeKey": "track_cycling",
    "parentTypeId": 2,
    "isHidden": false,
    "restricted": false,
    "trimmable": true
  },
  {
    "typeId": 22,
    "typeKey": "recumbent_cycling",
    "parentTypeId": 2,
    "isHidden": false,
    "restricted": false,
    "trimmable": true
  },
  {
    "typeId": 25,
    "typeKey": "indoor_cycling",
    "parentTypeId": 2,
    "isHidden": false,
    "restricted": false,
    "trimmable": true
  },
  {
    "typeId": 26,
    "typeKey": "swimming",
    "parentTypeId": 17,
    "isHidden": false,
    "restricted": false,
    "trimmable": true
  },
  {
    "typeId": 27,
    "typeKey": "lap_swimming",
    "parentTypeId": 26,
    "isHidden": false,
    "restricted": false,
    "trimmable": false
  },
  {
    "typeId": 28,
    "typeKey": "open_water_swimming",
    "parentTypeId": 26,
    "isHidden": false,
    "restricted": false,
    "trimmable": true
  },
  {
    "typeId": 29,
    "typeKey": "fitness_equipment",
    "parentTypeId": 17,
    "isHidden": false,
    "restricted": false,
    "trimmable": true
  },
  {
    "typeId": 30,
    "typeKey": "elliptical",
    "parentTypeId": 29,
    "isHidden": false,
    "restricted": false,
    "trimmable": true
  },
  {
    "typeId": 31,
    "typeKey": "stair_climbing",
    "parentTypeId": 29,
    "isHidden": false,
    "restricted": false,
    "trimmable": true
  },
  {
    "typeId": 32,
    "typeKey": "indoor_rowing",
    "parentTypeId": 29,
    "isHidden": false,
    "restricted": false,
    "trimmable": true
  },
  {
    "typeId": 37,
    "typeKey": "mountaineering",
    "parentTypeId": 4,
    "isHidden": false,
    "restricted": false,
    "trimmable": true
  },
  {
    "typeId": 41,
    "typeKey": "wind_kite_surfing",
    "parentTypeId": 4,
    "isHidden": false,
    "restricted": true,
    "trimmable": true
  },
  {
    "typeId": 44,
    "typeKey": "horseback_riding",
    "parentTypeId": 4,
    "isHidden": false,
    "restricted": false,
    "trimmable": true
  },
  {
    "typeId": 49,
    "typeKey": "driving_general",
    "parentTypeId": 4,
    "isHidden": false,
    "restricted": false,
    "trimmable": true
  },
  {
    "typeId": 52,
    "typeKey": "flying",
    "parentTypeId": 4,
    "isHidden": false,
    "restricted": false,
    "trimmable": true
  },
  {
    "typeId": 60,
    "typeKey": "whitewater_rafting_kayaking",
    "parentTypeId": 4,
    "isHidden": false,
    "restricted": true,
    "trimmable": true
  },
  {
    "typeId": 63,
    "typeKey": "inline_skating",
    "parentTypeId": 4,
    "isHidden": false,
    "restricted": false,
    "trimmable": true
  },
  {
    "typeId": 88,
    "typeKey": "golf",
    "parentTypeId": 4,
    "isHidden": false,
    "restricted": false,
    "trimmable": false
  },
  {
    "typeId": 89,
    "typeKey": "multi_sport",
    "parentTypeId": 17,
    "isHidden": false,
    "restricted": false,
    "trimmable": true
  },
  {
    "typeId": 108,
    "typeKey": "steps",
    "parentTypeId": 17,
    "isHidden": false,
    "restricted": false,
    "trimmable": true
  },
  {
    "typeId": 131,
    "typeKey": "bmx",
    "parentTypeId": 2,
    "isHidden": false,
    "restricted": false,
    "trimmable": true
  },
  {
    "typeId": 133,
    "typeKey": "hunting_fishing",
    "parentTypeId": 4,
    "isHidden": false,
    "restricted": true,
    "trimmable": true
  },
  {
    "typeId": 134,
    "typeKey": "sky_diving",
    "parentTypeId": 4,
    "isHidden": false,
    "restricted": false,
    "trimmable": true
  },
  {
    "typeId": 136,
    "typeKey": "rc_drone",
    "parentTypeId": 4,
    "isHidden": false,
    "restricted": false,
    "trimmable": true
  },
  {
    "typeId": 139,
    "typeKey": "rock_climbing",
    "parentTypeId": 4,
    "isHidden": false,
    "restricted": false,
    "trimmable": false
  },
  {
    "typeId": 140,
    "typeKey": "hang_gliding",
    "parentTypeId": 4,
    "isHidden": false,
    "restricted": false,
    "trimmable": true
  },
  {
    "typeId": 141,
    "typeKey": "wingsuit_flying",
    "parentTypeId": 4,
    "isHidden": false,
    "restricted": false,
    "trimmable": true
  },
  {
    "typeId": 143,
    "typeKey": "gravel_cycling",
    "parentTypeId": 2,
    "isHidden": false,
    "restricted": false,
    "trimmable": true
  },
  {
    "typeId": 144,
    "typeKey": "diving",
    "parentTypeId": 17,
    "isHidden": false,
    "restricted": false,
    "trimmable": false
  },
  {
    "typeId": 145,
    "typeKey": "single_gas_diving",
    "parentTypeId": 144,
    "isHidden": false,
    "restricted": false,
    "trimmable": false
  },
  {
    "typeId": 146,
    "typeKey": "multi_gas_diving",
    "parentTypeId": 144,
    "isHidden": false,
    "restricted": false,
    "trimmable": false
  },
  {
    "typeId": 147,
    "typeKey": "gauge_diving",
    "parentTypeId": 144,
    "isHidden": false,
    "restricted": false,
    "trimmable": false
  },
  {
    "typeId": 148,
    "typeKey": "apnea_diving",
    "parentTypeId": 144,
    "isHidden": false,
    "restricted": false,
    "trimmable": false
  },
  {
    "typeId": 150,
    "typeKey": "floor_climbing",
    "parentTypeId": 4,
    "isHidden": false,
    "restricted": false,
    "trimmable": true
  },
  {
    "typeId": 151,
    "typeKey": "stop_watch",
    "parentTypeId": 4,
    "isHidden": false,
    "restricted": false,
    "trimmable": true
  },
  {
    "typeId": 152,
    "typeKey": "virtual_ride",
    "parentTypeId": 2,
    "isHidden": false,
    "restricted": false,
    "trimmable": true
  },
  {
    "typeId": 153,
    "typeKey": "virtual_run",
    "parentTypeId": 1,
    "isHidden": false,
    "restricted": false,
    "trimmable": true
  },
  {
    "typeId": 154,
    "typeKey": "obstacle_run",
    "parentTypeId": 1,
    "isHidden": false,
    "restricted": false,
    "trimmable": true
  },
  {
    "typeId": 155,
    "typeKey": "apnea_hunting",
    "parentTypeId": 144,
    "isHidden": false,
    "restricted": false,
    "trimmable": false
  },
  {
    "typeId": 156,
    "typeKey": "indoor_running",
    "parentTypeId": 1,
    "isHidden": false,
    "restricted": false,
    "trimmable": true
  },
  {
    "typeId": 157,
    "typeKey": "safety",
    "parentTypeId": 17,
    "isHidden": false,
    "restricted": false,
    "trimmable": false
  },
  {
    "typeId": 158,
    "typeKey": "assistance",
    "parentTypeId": 157,
    "isHidden": false,
    "restricted": false,
    "trimmable": false
  },
  {
    "typeId": 159,
    "typeKey": "incident_detected",
    "parentTypeId": 157,
    "isHidden": false,
    "restricted": false,
    "trimmable": false
  },
  {
    "typeId": 160,
    "typeKey": "pilates",
    "parentTypeId": 29,
    "isHidden": false,
    "restricted": false,
    "trimmable": false
  },
  {
    "typeId": 161,
    "typeKey": "ccr_diving",
    "parentTypeId": 144,
    "isHidden": false,
    "restricted": false,
    "trimmable": false
  },
  {
    "typeId": 162,
    "typeKey": "auto_racing",
    "parentTypeId": 4,
    "isHidden": false,
    "restricted": false,
    "trimmable": true
  },
  {
    "typeId": 163,
    "typeKey": "yoga",
    "parentTypeId": 29,
    "isHidden": false,
    "restricted": false,
    "trimmable": false
  },
  {
    "typeId": 164,
    "typeKey": "breathwork",
    "parentTypeId": 4,
    "isHidden": false,
    "restricted": false,
    "trimmable": false
  },
  {
    "typeId": 165,
    "typeKey": "winter_sports",
    "parentTypeId": 17,
    "isHidden": false,
    "restricted": false,
    "trimmable": true
  },
  {
    "typeId": 166,
    "typeKey": "snowmobiling_ws",
    "parentTypeId": 165,
    "isHidden": false,
    "restricted": false,
    "trimmable": true
  },
  {
    "typeId": 167,
    "typeKey": "snow_shoe_ws",
    "parentTypeId": 165,
    "isHidden": false,
    "restricted": false,
    "trimmable": true
  },
  {
    "typeId": 168,
    "typeKey": "skating_ws",
    "parentTypeId": 165,
    "isHidden": false,
    "restricted": false,
    "trimmable": true
  },
  {
    "typeId": 169,
    "typeKey": "backcountry_skiing_snowboarding_ws",
    "parentTypeId": 165,
    "isHidden": false,
    "restricted": true,
    "trimmable": false
  },
  {
    "typeId": 170,
    "typeKey": "skate_skiing_ws",
    "parentTypeId": 165,
    "isHidden": false,
    "restricted": false,
    "trimmable": true
  },
  {
    "typeId": 171,
    "typeKey": "cross_country_skiing_ws",
    "parentTypeId": 165,
    "isHidden": false,
    "restricted": false,
    "trimmable": true
  },
  {
    "typeId": 172,
    "typeKey": "resort_skiing_snowboarding_ws",
    "parentTypeId": 165,
    "isHidden": false,
    "restricted": true,
    "trimmable": false
  },
  {
    "typeId": 173,
    "typeKey": "indoor_climbing",
    "parentTypeId": 29,
    "isHidden": false,
    "restricted": false,
    "trimmable": false
  },
  {
    "typeId": 174,
    "typeKey": "bouldering",
    "parentTypeId": 29,
    "isHidden": false,
    "restricted": false,
    "trimmable": false
  },
  {
    "typeId": 175,
    "typeKey": "e_bike_mountain",
    "parentTypeId": 2,
    "isHidden": false,
    "restricted": false,
    "trimmable": true
  },
  {
    "typeId": 176,
    "typeKey": "e_bike_fitness",
    "parentTypeId": 2,
    "isHidden": false,
    "restricted": false,
    "trimmable": true
  },
  {
    "typeId": 180,
    "typeKey": "hiit",
    "parentTypeId": 29,
    "isHidden": false,
    "restricted": false,
    "trimmable": false
  },
  {
    "typeId": 181,
    "typeKey": "ultra_run",
    "parentTypeId": 1,
    "isHidden": false,
    "restricted": false,
    "trimmable": true
  },
  {
    "typeId": 182,
    "typeKey": "e_sport",
    "parentTypeId": 4,
    "isHidden": false,
    "restricted": false,
    "trimmable": false
  },
  {
    "typeId": 185,
    "typeKey": "motorcycling_v2",
    "parentTypeId": 4,
    "isHidden": false,
    "restricted": false,
    "trimmable": true
  },
  {
    "typeId": 186,
    "typeKey": "motocross_v2",
    "parentTypeId": 4,
    "isHidden": false,
    "restricted": false,
    "trimmable": true
  },
  {
    "typeId": 187,
    "typeKey": "atv_v2",
    "parentTypeId": 4,
    "isHidden": false,
    "restricted": false,
    "trimmable": true
  },
  {
    "typeId": 189,
    "typeKey": "transition_v2",
    "parentTypeId": 4,
    "isHidden": false,
    "restricted": false,
    "trimmable": true
  },
  {
    "typeId": 190,
    "typeKey": "swimToBikeTransition_v2",
    "parentTypeId": 4,
    "isHidden": false,
    "restricted": false,
    "trimmable": true
  },
  {
    "typeId": 191,
    "typeKey": "bikeToRunTransition_v2",
    "parentTypeId": 4,
    "isHidden": false,
    "restricted": false,
    "trimmable": true
  },
  {
    "typeId": 192,
    "typeKey": "runToBikeTransition_v2",
    "parentTypeId": 4,
    "isHidden": false,
    "restricted": false,
    "trimmable": true
  },
  {
    "typeId": 193,
    "typeKey": "hunting",
    "parentTypeId": 4,
    "isHidden": false,
    "restricted": false,
    "trimmable": true
  },
  {
    "typeId": 197,
    "typeKey": "hand_cycling",
    "parentTypeId": 2,
    "isHidden": false,
    "restricted": false,
    "trimmable": true
  },
  {
    "typeId": 198,
    "typeKey": "indoor_hand_cycling",
    "parentTypeId": 2,
    "isHidden": false,
    "restricted": false,
    "trimmable": true
  },
  {
    "typeId": 199,
    "typeKey": "para_sports",
    "parentTypeId": 17,
    "isHidden": false,
    "restricted": false,
    "trimmable": true
  },
  {
    "typeId": 200,
    "typeKey": "wheelchair_push_run",
    "parentTypeId": 199,
    "isHidden": false,
    "restricted": false,
    "trimmable": true
  },
  {
    "typeId": 201,
    "typeKey": "wheelchair_push_walk",
    "parentTypeId": 199,
    "isHidden": false,
    "restricted": false,
    "trimmable": true
  },
  {
    "typeId": 202,
    "typeKey": "meditation",
    "parentTypeId": 4,
    "isHidden": false,
    "restricted": false,
    "trimmable": false
  },
  {
    "typeId": 203,
    "typeKey": "backcountry_skiing",
    "parentTypeId": 165,
    "isHidden": false,
    "restricted": false,
    "trimmable": false
  },
  {
    "typeId": 204,
    "typeKey": "backcountry_snowboarding",
    "parentTypeId": 165,
    "isHidden": false,
    "restricted": false,
    "trimmable": false
  },
  {
    "typeId": 205,
    "typeKey": "disc_golf",
    "parentTypeId": 4,
    "isHidden": false,
    "restricted": false,
    "trimmable": true
  },
  {
    "typeId": 206,
    "typeKey": "team_sports",
    "parentTypeId": 17,
    "isHidden": false,
    "restricted": false,
    "trimmable": true
  },
  {
    "typeId": 207,
    "typeKey": "cricket",
    "parentTypeId": 206,
    "isHidden": false,
    "restricted": false,
    "trimmable": true
  },
  {
    "typeId": 208,
    "typeKey": "rugby",
    "parentTypeId": 206,
    "isHidden": false,
    "restricted": false,
    "trimmable": true
  },
  {
    "typeId": 209,
    "typeKey": "ice_hockey",
    "parentTypeId": 206,
    "isHidden": false,
    "restricted": false,
    "trimmable": true
  },
  {
    "typeId": 210,
    "typeKey": "field_hockey",
    "parentTypeId": 206,
    "isHidden": false,
    "restricted": false,
    "trimmable": true
  },
  {
    "typeId": 211,
    "typeKey": "lacrosse",
    "parentTypeId": 206,
    "isHidden": false,
    "restricted": false,
    "trimmable": true
  },
  {
    "typeId": 212,
    "typeKey": "volleyball",
    "parentTypeId": 206,
    "isHidden": false,
    "restricted": false,
    "trimmable": true
  },
  {
    "typeId": 213,
    "typeKey": "ultimate_disc",
    "parentTypeId": 206,
    "isHidden": false,
    "restricted": false,
    "trimmable": true
  },
  {
    "typeId": 214,
    "typeKey": "softball",
    "parentTypeId": 206,
    "isHidden": false,
    "restricted": false,
    "trimmable": true
  },
  {
    "typeId": 215,
    "typeKey": "soccer",
    "parentTypeId": 206,
    "isHidden": false,
    "restricted": false,
    "trimmable": true
  },
  {
    "typeId": 216,
    "typeKey": "american_football",
    "parentTypeId": 206,
    "isHidden": false,
    "restricted": false,
    "trimmable": true
  },
  {
    "typeId": 217,
    "typeKey": "basketball",
    "parentTypeId": 206,
    "isHidden": false,
    "restricted": false,
    "trimmable": true
  },
  {
    "typeId": 218,
    "typeKey": "baseball",
    "parentTypeId": 206,
    "isHidden": false,
    "restricted": false,
    "trimmable": true
  },
  {
    "typeId": 219,
    "typeKey": "racket_sports",
    "parentTypeId": 17,
    "isHidden": false,
    "restricted": false,
    "trimmable": true
  },
  {
    "typeId": 220,
    "typeKey": "table_tennis",
    "parentTypeId": 219,
    "isHidden": false,
    "restricted": false,
    "trimmable": true
  },
  {
    "typeId": 221,
    "typeKey": "platform_tennis",
    "parentTypeId": 219,
    "isHidden": false,
    "restricted": false,
    "trimmable": true
  },
  {
    "typeId": 222,
    "typeKey": "racquetball",
    "parentTypeId": 219,
    "isHidden": false,
    "restricted": false,
    "trimmable": true
  },
  {
    "typeId": 223,
    "typeKey": "squash",
    "parentTypeId": 219,
    "isHidden": false,
    "restricted": false,
    "trimmable": true
  },
  {
    "typeId": 224,
    "typeKey": "badminton",
    "parentTypeId": 219,
    "isHidden": false,
    "restricted": false,
    "trimmable": true
  },
  {
    "typeId": 225,
    "typeKey": "pickleball",
    "parentTypeId": 219,
    "isHidden": false,
    "restricted": false,
    "trimmable": true
  },
  {
    "typeId": 226,
    "typeKey": "paddelball",
    "parentTypeId": 219,
    "isHidden": false,
    "restricted": false,
    "trimmable": true
  },
  {
    "typeId": 227,
    "typeKey": "tennis_v2",
    "parentTypeId": 219,
    "isHidden": false,
    "restricted": false,
    "trimmable": true
  },
  {
    "typeId": 228,
    "typeKey": "water_sports",
    "parentTypeId": 17,
    "isHidden": false,
    "restricted": false,
    "trimmable": true
  },
  {
    "typeId": 229,
    "typeKey": "boating_v2",
    "parentTypeId": 228,
    "isHidden": false,
    "restricted": false,
    "trimmable": true
  },
  {
    "typeId": 230,
    "typeKey": "fishing_v2",
    "parentTypeId": 228,
    "isHidden": false,
    "restricted": false,
    "trimmable": true
  },
  {
    "typeId": 231,
    "typeKey": "kayaking_v2",
    "parentTypeId": 228,
    "isHidden": false,
    "restricted": false,
    "trimmable": true
  },
  {
    "typeId": 232,
    "typeKey": "kiteboarding_v2",
    "parentTypeId": 228,
    "isHidden": false,
    "restricted": false,
    "trimmable": true
  },
  {
    "typeId": 233,
    "typeKey": "offshore_grinding_v2",
    "parentTypeId": 228,
    "isHidden": false,
    "restricted": false,
    "trimmable": true
  },
  {
    "typeId": 234,
    "typeKey": "onshore_grinding_v2",
    "parentTypeId": 29,
    "isHidden": false,
    "restricted": false,
    "trimmable": true
  },
  {
    "typeId": 235,
    "typeKey": "paddling_v2",
    "parentTypeId": 228,
    "isHidden": false,
    "restricted": false,
    "trimmable": true
  },
  {
    "typeId": 236,
    "typeKey": "whitewater_rafting_v2",
    "parentTypeId": 228,
    "isHidden": false,
    "restricted": false,
    "trimmable": true
  },
  {
    "typeId": 237,
    "typeKey": "rowing_v2",
    "parentTypeId": 228,
    "isHidden": false,
    "restricted": false,
    "trimmable": true
  },
  {
    "typeId": 238,
    "typeKey": "sailing_v2",
    "parentTypeId": 228,
    "isHidden": false,
    "restricted": false,
    "trimmable": true
  },
  {
    "typeId": 239,
    "typeKey": "stand_up_paddleboarding_v2",
    "parentTypeId": 228,
    "isHidden": false,
    "restricted": false,
    "trimmable": true
  },
  {
    "typeId": 240,
    "typeKey": "surfing_v2",
    "parentTypeId": 228,
    "isHidden": false,
    "restricted": false,
    "trimmable": false
  },
  {
    "typeId": 241,
    "typeKey": "water_tubing",
    "parentTypeId": 228,
    "isHidden": false,
    "restricted": false,
    "trimmable": false
  },
  {
    "typeId": 242,
    "typeKey": "windsurfing_v2",
    "parentTypeId": 228,
    "isHidden": false,
    "restricted": false,
    "trimmable": true
  },
  {
    "typeId": 243,
    "typeKey": "wakeboarding_v2",
    "parentTypeId": 228,
    "isHidden": false,
    "restricted": false,
    "trimmable": false
  },
  {
    "typeId": 244,
    "typeKey": "wakesurfing",
    "parentTypeId": 228,
    "isHidden": false,
    "restricted": false,
    "trimmable": false
  },
  {
    "typeId": 245,
    "typeKey": "waterskiing",
    "parentTypeId": 228,
    "isHidden": false,
    "restricted": false,
    "trimmable": false
  },
  {
    "typeId": 246,
    "typeKey": "boxing",
    "parentTypeId": 4,
    "isHidden": false,
    "restricted": false,
    "trimmable": true
  },
  {
    "typeId": 247,
    "typeKey": "archery",
    "parentTypeId": 4,
    "isHidden": false,
    "restricted": false,
    "trimmable": true
  },
  {
    "typeId": 248,
    "typeKey": "mixed_martial_arts",
    "parentTypeId": 4,
    "isHidden": false,
    "restricted": false,
    "trimmable": true
  },
  {
    "typeId": 249,
    "typeKey": "overland",
    "parentTypeId": 4,
    "isHidden": false,
    "restricted": false,
    "trimmable": true
  },
  {
    "typeId": 250,
    "typeKey": "snorkeling",
    "parentTypeId": 228,
    "isHidden": false,
    "restricted": false,
    "trimmable": true
  },
  {
    "typeId": 251,
    "typeKey": "resort_skiing",
    "parentTypeId": 165,
    "isHidden": false,
    "restricted": false,
    "trimmable": true
  },
  {
    "typeId": 252,
    "typeKey": "resort_snowboarding",
    "parentTypeId": 165,
    "isHidden": false,
    "restricted": false,
    "trimmable": true
  },
  {
    "typeId": 253,
    "typeKey": "dance",
    "parentTypeId": 29,
    "isHidden": false,
    "restricted": false,
    "trimmable": false
  },
  {
    "typeId": 254,
    "typeKey": "jump_rope",
    "parentTypeId": 29,
    "isHidden": false,
    "restricted": false,
    "trimmable": false
  },
  {
    "typeId": 255,
    "typeKey": "mobility",
    "parentTypeId": 29,
    "isHidden": false,
    "restricted": false,
    "trimmable": false
  },
  {
    "typeId": 256,
    "typeKey": "enduro_mtb",
    "parentTypeId": 2,
    "isHidden": false,
    "restricted": false,
    "trimmable": true
  },
  {
    "typeId": 257,
    "typeKey": "rucking",
    "parentTypeId": 3,
    "isHidden": false,
    "restricted": false,
    "trimmable": true
  },
  {
    "typeId": 259,
    "typeKey": "pool_apnea",
    "parentTypeId": 144,
    "isHidden": false,
    "restricted": false,
    "trimmable": false
  },
  {
    "typeId": 260,
    "typeKey": "e_enduro_mtb",
    "parentTypeId": 2,
    "isHidden": false,
    "restricted": false,
    "trimmable": true
  }
]
